{
  "name": "dartantic_ai",
  "description": "An agent framework inspired by pydantic-ai and designed to make building client and server-side apps in Dart with generative AI easier and more fun!",
  "theme": {
    "primary": "#0175C2"
  },
  "logo": {
    "light": "/images/dartantic-logo-light.png",
    "dark": "/images/dartantic-logo-dark.png"
  },
  "header": {
    "showName": false
  },
  "sidebar": [
    {
      "group": "Getting Started",
      "pages": [
        {
          "title": "Welcome",
          "href": "/"
        },
        {
          "title": "Quick Start",
          "href": "/quick-start"
        },
        {
          "title": "Agentic Behavior",
          "href": "/agentic-behavior"
        },
        {
          "title": "Providers",
          "href": "/providers"
        },
        {
          "title": "Migration Guide",
          "href": "/migration-guide"
        }
      ]
    },
    {
      "group": "Features",
      "pages": [
        {
          "title": "Streaming Output",
          "href": "/streaming-output"
        },
        {
          "title": "Multi-turn Chat",
          "href": "/multi-turn-chat"
        },
        {
          "title": "Typed Output",
          "href": "/typed-output"
        },
        {
          "title": "Tool Calling",
          "href": "/tool-calling"
        },
        {
          "title": "System Messages",
          "href": "/system-messages"
        },
        {
          "title": "Multi-Media Input",
          "href": "/multi-media-input"
        }
      ]
    },
    {
      "group": "Advanced",
      "pages": [
        {
          "title": "Embeddings",
          "href": "/embeddings"
        },
        {
          "title": "Usage Tracking",
          "href": "/usage-tracking"
        },
        {
          "title": "Automatic Retry",
          "href": "/automatic-retry"
        },
        {
          "title": "Logging",
          "href": "/logging"
        },
        {
          "title": "Custom Providers",
          "href": "/custom-providers"
        }
      ]
    },
    {
      "group": "Integration",
      "pages": [
        {
          "title": "Environment Setup",
          "href": "/environment-setup"
        },
        {
          "title": "MCP Server Support",
          "href": "/mcp-support"
        },
        {
          "title": "Using DotPrompt",
          "href": "/using-dotprompt"
        }
      ]
    },
    {
      "group": "Miscellaneous",
      "pages": [
        {
          "title": "Notes On AI Codegen",
          "href": "/notes-on-ai-codegen"
        },
        {
          "title": "Contributing",
          "href": "/contributing"
        },
        {
          "title": "Discussion ↗",
          "href": "https://github.com/csells/dartantic_ai/discussions"
        },
        {
          "title": "API Reference ↗",
          "href": "https://pub.dev/documentation/dartantic_ai/latest/"
        }
      ]
    }
  ]
}